quanturf_blankly/__init__.py
quanturf_blankly/__main__.py
quanturf_blankly-0.5.dist-info/METADATA
quanturf_blankly-0.5.dist-info/WHEEL
quanturf_blankly-0.5.dist-info/entry_points.txt
quanturf_blankly-0.5.dist-info/top_level.txt
quanturf_blankly-0.5.dist-info/RECORD
