Metadata-Version: 2.1
Name: quanturf-blankly
Version: 0.5
Home-page: https://github.com/Quanturf/quanturf_blankly_package
Author: Quanturf
Author-email: quanturf.finance@gmail.com
Classifier: Intended Audience :: Developers
Classifier: Intended Audience :: System Administrators
Classifier: Intended Audience :: Science/Research
Classifier: License :: OSI Approved :: GNU General Public License v3 (GPLv3)
Classifier: Programming Language :: Python
Classifier: Programming Language :: Python :: 3
Requires-Dist: blankly
Requires-Dist: apscheduler
Requires-Dist: thread6
Requires-Dist: alpaca-trade-api
Requires-Dist: pandas
Requires-Dist: numpy
